meissa/__init__.py
meissa/__main__.py
meissa/meissa.py
meissa/primitives/__init__.py
meissa-0.0.1.dev0.dist-info/AUTHORS.rst
meissa-0.0.1.dev0.dist-info/LICENSE
meissa-0.0.1.dev0.dist-info/METADATA
meissa-0.0.1.dev0.dist-info/WHEEL
meissa-0.0.1.dev0.dist-info/entry_points.txt
meissa-0.0.1.dev0.dist-info/top_level.txt
meissa-0.0.1.dev0.dist-info/RECORD
